kumoai/__init__.py
kumoai/_logging.py
kumoai/_singleton.py
kumoai/_version.py
kumoai/databricks.py
kumoai/exceptions.py
kumoai/formatting.py
kumoai/futures.py
kumoai/jobs.py
kumoai/mixin.py
kumoai/spcs.py
kumoai/artifact_export/__init__.py
kumoai/artifact_export/config.py
kumoai/artifact_export/job.py
kumoai/client/__init__.py
kumoai/client/client.py
kumoai/client/connector.py
kumoai/client/endpoints.py
kumoai/client/graph.py
kumoai/client/jobs.py
kumoai/client/online.py
kumoai/client/pquery.py
kumoai/client/rfm.py
kumoai/client/source_table.py
kumoai/client/table.py
kumoai/client/utils.py
kumoai/codegen/__init__.py
kumoai/codegen/cli.py
kumoai/codegen/context.py
kumoai/codegen/edits.py
kumoai/codegen/exceptions.py
kumoai/codegen/generate.py
kumoai/codegen/identity.py
kumoai/codegen/loader.py
kumoai/codegen/naming.py
kumoai/codegen/registry.py
kumoai/codegen/handlers/__init__.py
kumoai/codegen/handlers/connector.py
kumoai/codegen/handlers/graph.py
kumoai/codegen/handlers/pquery.py
kumoai/codegen/handlers/table.py
kumoai/codegen/handlers/utils.py
kumoai/connector/__init__.py
kumoai/connector/base.py
kumoai/connector/bigquery_connector.py
kumoai/connector/databricks_connector.py
kumoai/connector/file_upload_connector.py
kumoai/connector/glue_connector.py
kumoai/connector/s3_connector.py
kumoai/connector/snowflake_connector.py
kumoai/connector/source_table.py
kumoai/connector/utils.py
kumoai/encoder/__init__.py
kumoai/experimental/__init__.py
kumoai/experimental/rfm/__init__.py
kumoai/experimental/rfm/authenticate.py
kumoai/experimental/rfm/local_graph.py
kumoai/experimental/rfm/local_graph_sampler.py
kumoai/experimental/rfm/local_graph_store.py
kumoai/experimental/rfm/local_pquery_driver.py
kumoai/experimental/rfm/local_table.py
kumoai/experimental/rfm/rfm.py
kumoai/experimental/rfm/utils.py
kumoai/experimental/rfm/infer/__init__.py
kumoai/experimental/rfm/infer/categorical.py
kumoai/experimental/rfm/infer/id.py
kumoai/experimental/rfm/infer/multicategorical.py
kumoai-2.12.0.dist-info/licenses/LICENSE
kumoai-2.12.0.dist-info/METADATA
kumoai-2.12.0.dist-info/WHEEL
kumoai-2.12.0.dist-info/top_level.txt
kumoai-2.12.0.dist-info/RECORD
