Metadata-Version: 2.4
Name: kumoai
Version: 2.12.0
Summary: AI on the Modern Data Stack
Author-email: "Kumo.AI" <hello@kumo.ai>
License-Expression: MIT
Project-URL: homepage, https://kumo.ai
Project-URL: documentation, https://kumo.ai/docs
Keywords: deep-learning,graph-neural-networks,cloud-data-warehouse
Classifier: Development Status :: 5 - Production/Stable
Classifier: Programming Language :: Python
Classifier: Programming Language :: Python :: 3.10
Classifier: Programming Language :: Python :: 3.11
Classifier: Programming Language :: Python :: 3.12
Classifier: Programming Language :: Python :: 3.13
Classifier: Programming Language :: Python :: 3 :: Only
Requires-Python: >=3.10
License-File: LICENSE
Requires-Dist: pandas
Requires-Dist: pyarrow<19.0.0,>=8.0.0
Requires-Dist: requests>=2.28.2
Requires-Dist: urllib3
Requires-Dist: plotly
Requires-Dist: typing_extensions>=4.5.0
Requires-Dist: kumo-api==0.45.0
Requires-Dist: tqdm>=4.66.0
Requires-Dist: aiohttp>=3.10.0
Requires-Dist: pydantic>=1.10.21
Requires-Dist: rich>=9.0.0
Provides-Extra: doc
Requires-Dist: sphinx; extra == "doc"
Requires-Dist: sphinx-book-theme; extra == "doc"
Requires-Dist: sphinx-copybutton; extra == "doc"
Requires-Dist: sphinx-autodoc-typehints; extra == "doc"
Requires-Dist: graphviz; extra == "doc"
Provides-Extra: test
Requires-Dist: pytest; extra == "test"
Requires-Dist: pytest-mock; extra == "test"
Requires-Dist: requests-mock; extra == "test"
Dynamic: license-file
Dynamic: requires-dist
